<?xml version="1.0"?>
<!--<!DOCTYPE metadata SYSTEM "http://www.esri.com/metadata/esriprof80.dtd">-->
<metadata xml:lang="en"><Esri><CreaDate>20100609</CreaDate><CreaTime>12183600</CreaTime><SyncOnce>TRUE</SyncOnce><MetaID>{D8CB032C-EC45-475F-AAB4-62EFEA01FD9E}</MetaID></Esri><idinfo><citation><citeinfo><onlink Sync="TRUE">\\NARSS\J\CBSIRS\Victory12-Area 9-6-2010\codes\semantics\store\newarea\water\water_train</onlink></citeinfo></citation></idinfo><distInfo><distributor><distorTran><onLineSrc><linkage Sync="TRUE">file://\\NARSS\J\CBSIRS\Victory12-Area 9-6-2010\codes\semantics\store\newarea\water\water_train</linkage><protocol Sync="TRUE">Local Area Network</protocol></onLineSrc></distorTran></distributor></distInfo><dataqual><lineage><procstep><procdesc Sync="TRUE">Dataset copied.</procdesc><srcused Sync="TRUE">I:\CBSIRS\Victory12-Area 7-6-2010\codes\semantics\store\newarea\water_test</srcused><procdate Sync="TRUE">20100609</procdate><proctime Sync="TRUE">12183600</proctime></procstep><procstep><procdesc Sync="TRUE">Dataset moved.</procdesc><srcused Sync="TRUE">J:\CBSIRS\Victory12-Area 9-6-2010\codes\semantics\store\newarea\water_train</srcused><date Sync="TRUE">20100612</date><time Sync="TRUE">10155200</time></procstep></lineage></dataqual></metadata>
